LICENSE.txt
README.md
setup.cfg
setup.py
airflow_prima_providers/__init__.py
airflow_prima_providers/catalog_glue_operator.py
airflow_prima_providers.egg-info/PKG-INFO
airflow_prima_providers.egg-info/SOURCES.txt
airflow_prima_providers.egg-info/dependency_links.txt
airflow_prima_providers.egg-info/requires.txt
airflow_prima_providers.egg-info/top_level.txt
airflow_prima_providers/example_dags/__init__.py
airflow_prima_providers/glue_custom_crawler/__init__.py
airflow_prima_providers/glue_custom_crawler/descriptors.py
airflow_prima_providers/glue_custom_crawler/glue_crawler.py
airflow_prima_providers/glue_custom_crawler/managers.py
airflow_prima_providers/hooks/__init__.py
airflow_prima_providers/hooks/datadog.py
airflow_prima_providers/operators/__init__.py
airflow_prima_providers/operators/check_schema_glue_operator.py
airflow_prima_providers/operators/crawler_glue_operator.py
airflow_prima_providers/operators/datadog_operator.py
airflow_prima_providers/operators/dynamodb_operator.py
airflow_prima_providers/operators/dynamodb_resource.py
airflow_prima_providers/operators/emr_submit_and_monitor_step_operator.py
airflow_prima_providers/operators/glue_custom_crawler_operator.py