Metadata-Version: 2.1
Name: airflow-prima-providers
Version: 0.8
Summary: Airflow utility providers developed by Prima Assicurazioni
Home-page: https://github.com/albanovito/providers-prima
Author: Prima Assicurazioni
Author-email: team-data@prima.it
License: MIT
Download-URL: https://github.com/albanovito/providers-prima/archive/refs/tags/0.8.tar.gz
Keywords: airflow,prima,providers
Platform: UNKNOWN
Classifier: Development Status :: 3 - Alpha
Classifier: Intended Audience :: Developers
Classifier: Topic :: Software Development :: Build Tools
Classifier: License :: OSI Approved :: MIT License
Classifier: Programming Language :: Python :: 3.8
Classifier: Programming Language :: Python :: 3.9
License-File: LICENSE.txt
